jupyter_embed/__init__.py
jupyter_embed/__main__.py
jupyter_embed/_version.py
jupyter_embed/application.py
jupyter_embed/serverapplication.py
jupyter_embed/handlers/__init__.py
jupyter_embed/handlers/base.py
jupyter_embed/handlers/config/__init__.py
jupyter_embed/handlers/config/handler.py
jupyter_embed/handlers/docker/__init__.py
jupyter_embed/handlers/docker/handler.py
jupyter_embed/handlers/echo/__init__.py
jupyter_embed/handlers/echo/handler.py
jupyter_embed/handlers/index/__init__.py
jupyter_embed/handlers/index/handler.py
jupyter_embed/handlers/ping/__init__.py
jupyter_embed/handlers/ping/handler.py
jupyter_embed/handlers/proxy/__init__.py
jupyter_embed/handlers/proxy/handler.py
jupyter_embed/handlers/relay/__init__.py
jupyter_embed/handlers/relay/handler.py
jupyter_embed/static/102.jupyter-embed.js
jupyter_embed/static/1020.jupyter-embed.js
jupyter_embed/static/1050.jupyter-embed.js
jupyter_embed/static/1109.jupyter-embed.js
jupyter_embed/static/1110.jupyter-embed.js
jupyter_embed/static/1146.jupyter-embed.js
jupyter_embed/static/1292.jupyter-embed.js
jupyter_embed/static/1450.jupyter-embed.js
jupyter_embed/static/1626.jupyter-embed.js
jupyter_embed/static/1629.jupyter-embed.js
jupyter_embed/static/1696.jupyter-embed.js
jupyter_embed/static/1810.jupyter-embed.js
jupyter_embed/static/1900.jupyter-embed.js
jupyter_embed/static/1919.jupyter-embed.js
jupyter_embed/static/1956.jupyter-embed.js
jupyter_embed/static/2.jupyter-embed.js
jupyter_embed/static/2003.jupyter-embed.js
jupyter_embed/static/2030.jupyter-embed.js
jupyter_embed/static/2066.jupyter-embed.js
jupyter_embed/static/2074.jupyter-embed.js
jupyter_embed/static/2086.jupyter-embed.js
jupyter_embed/static/2148.jupyter-embed.js
jupyter_embed/static/2218.jupyter-embed.js
jupyter_embed/static/2322.jupyter-embed.js
jupyter_embed/static/2464.jupyter-embed.js
jupyter_embed/static/2529.jupyter-embed.js
jupyter_embed/static/2548.jupyter-embed.js
jupyter_embed/static/2579.jupyter-embed.js
jupyter_embed-0.0.1.dist-info/METADATA
jupyter_embed-0.0.1.dist-info/WHEEL
jupyter_embed-0.0.1.dist-info/entry_points.txt
jupyter_embed-0.0.1.dist-info/licenses/LICENSE
jupyter_embed-0.0.1.dist-info/RECORD
